truckersmp/__init__.py
truckersmp/base.py
truckersmp/baseExceptions.py
truckersmp.py-1.0.0.2.dist-info/LICENSE
truckersmp.py-1.0.0.2.dist-info/METADATA
truckersmp.py-1.0.0.2.dist-info/WHEEL
truckersmp.py-1.0.0.2.dist-info/top_level.txt
truckersmp.py-1.0.0.2.dist-info/RECORD
