Metadata-Version: 2.1
Name: truckersmp.py
Version: 1.0.0.2
Summary: Simple API Wrapper for the TruckersMP API
Home-page: https://github.com/supraaxdd/truckersmp-api
Author: Itz Blinkzy, supraaxdd
Author-email: legendarystone12@gmail.com, supra6950@gmail.com
License: GNU
Keywords: api wrapper truckersmp
Platform: UNKNOWN
Classifier: Programming Language :: Python :: 3
Classifier: License :: OSI Approved :: GNU General Public License v3 or later (GPLv3+)
Classifier: Operating System :: OS Independent
Requires-Python: >=3.7
